MPALP/__init__.py
MPALP/accuracy/__init__.py
MPALP/accuracy/classificationutils.py
MPALP/lossfunction/__init__.py
MPALP/lossfunction/lossfunction.py
MPALP/trainer/__init__.py
MPALP/trainer/train.py
MPALP/trainer/trainutils.py
MPALP/utils/__init__.py
MPALP/utils/timeutils.py
mpalp-0.1.4.dist-info/METADATA
mpalp-0.1.4.dist-info/WHEEL
mpalp-0.1.4.dist-info/top_level.txt
mpalp-0.1.4.dist-info/RECORD
