Metadata-Version: 2.4
Name: mpalp
Version: 0.1.4
Summary: Multi-Purpose AI Learning Package
Author: Kimyh
Author-email: kim_yh663927@naver.com
Classifier: Programming Language :: Python :: 3
Classifier: License :: OSI Approved :: MIT License
Classifier: Operating System :: OS Independent
Requires-Python: >=3.10
Requires-Dist: torch==2.7.0
Requires-Dist: torchaudio==2.7.0
Requires-Dist: torchvision==0.22.0
Requires-Dist: pandas==2.2.3
Requires-Dist: psutil==7.0.0
Requires-Dist: tqdm==4.67.1
Dynamic: author
Dynamic: author-email
Dynamic: classifier
Dynamic: description
Dynamic: description-content-type
Dynamic: requires-dist
Dynamic: requires-python
Dynamic: summary
